{
	"id": "episode1",
	"name": "The Beginning",
	"description": "Your journey begins here",
	"grid_size": [
		9.0,
		9.0
	],
	"available_heroes": [
		"knight"
	],
	"entry_points": [
		[
			1.0,
			1.0
		],
		[
			7.0,
			1.0
		],
		[
			1.0,
			7.0
		]
	],
	"entities": [
		{
			"type": "enemy",
			"id": "orc",
			"position": [
				1.0,
				5.0
			]
		},
		{
			"type": "enemy",
			"id": "orc",
			"position": [
				1.0,
				1.0
			]
		},
		{
			"type": "enemy",
			"id": "orc",
			"position": [
				1.0,
				2.0
			]
		},
		{
			"type": "enemy",
			"id": "orc",
			"position": [
				1.0,
				3.0
			]
		},
		{
			"type": "object",
			"id": "rock",
			"position": [
				5.0,
				5.0
			]
		}
	],
	"objectives": [
		"Defeat the orc",
		"Reach the exit"
	]
}